neurostatx/__init__.py
neurostatx/cli/AddNodesAttributes.py
neurostatx/cli/ApplyModel.py
neurostatx/cli/AverageWeightedPath.py
neurostatx/cli/CompareClustering.py
neurostatx/cli/CompareGraphs.py
neurostatx/cli/ComputeGraphNetwork.py
neurostatx/cli/ConfirmatoryFA.py
neurostatx/cli/ExploratoryFA.py
neurostatx/cli/FuzzyClustering.py
neurostatx/cli/GraphMetrics.py
neurostatx/cli/LogisticRegression.py
neurostatx/cli/PartialLeastSquareRegression.py
neurostatx/cli/PredictFuzzyMembership.py
neurostatx/cli/VisualizeGraphNetwork.py
neurostatx/cli/__init__.py
neurostatx/clustering/__init__.py
neurostatx/clustering/distance.py
neurostatx/clustering/fuzzy.py
neurostatx/clustering/metrics.py
neurostatx/clustering/viz.py
neurostatx/io/__init__.py
neurostatx/io/download.py
neurostatx/io/loader.py
neurostatx/io/utils.py
neurostatx/io/viz.py
neurostatx/network/__init__.py
neurostatx/network/metrics.py
neurostatx/network/utils.py
neurostatx/network/viz.py
neurostatx/statistics/__init__.py
neurostatx/statistics/harmonization.py
neurostatx/statistics/models.py
neurostatx/statistics/utils.py
neurostatx/tests/test_add_nodes_attributes.py
neurostatx/tests/test_applymodel.py
neurostatx/tests/test_clustering_metrics.py
neurostatx/tests/test_compare_clustering.py
neurostatx/tests/test_compare_graphs.py
neurostatx/tests/test_compute_graph_network.py
neurostatx/tests/test_compute_weighted_path.py
neurostatx/tests/test_confirmatoryfa.py
neurostatx/tests/test_exploratoryfa.py
neurostatx/tests/test_factor.py
neurostatx/tests/test_fuzzy.py
neurostatx/tests/test_fuzzy_clustering.py
neurostatx/tests/test_fuzzylabelers.py
neurostatx/tests/test_graph_metrics.py
neurostatx/tests/test_harmonization.py
neurostatx/tests/test_loaders.py
neurostatx/tests/test_logistic_regression.py
neurostatx/tests/test_partial_least_square.py
neurostatx/tests/test_predict_fuzzy_membership.py
neurostatx/tests/test_preprocessing.py
neurostatx/tests/test_statistics_models.py
neurostatx/tests/test_statistics_utils.py
neurostatx-0.1.1.dist-info/LICENSE
neurostatx-0.1.1.dist-info/METADATA
neurostatx-0.1.1.dist-info/WHEEL
neurostatx-0.1.1.dist-info/entry_points.txt
neurostatx-0.1.1.dist-info/RECORD
