Metadata-Version: 2.1
Name: NeuroStatX
Version: 0.1.1
Summary: Command-line toolbox to perform various statistical analysis on neuroscience data.
Home-page: https://github.com/gagnonanthony/NeuroStatX.git
License: MIT
Author: Anthony Gagnon
Author-email: anthony.gagnon7@usherbrooke.ca
Requires-Python: >=3.10,<3.12
Classifier: License :: OSI Approved :: MIT License
Classifier: Programming Language :: Python :: 3
Classifier: Programming Language :: Python :: 3.10
Classifier: Programming Language :: Python :: 3.11
Requires-Dist: Pillow (>=10.3.0,<11.0.0)
Requires-Dist: coloredlogs (>=15.0.1,<16.0.0)
Requires-Dist: cyclopts (>=2.2.0,<3.0.0)
Requires-Dist: detect-delimiter (>=0.1.1,<0.2.0)
Requires-Dist: factor-analyzer (>=0.5.0,<0.6.0)
Requires-Dist: gdown (==5.1.0)
Requires-Dist: graphviz (>=0.20.1,<0.21.0)
Requires-Dist: ipykernel (>=6.29.5,<7.0.0)
Requires-Dist: kneed (>=0.8.5,<0.9.0)
Requires-Dist: matplotlib (>=3.8.2,<4.0.0)
Requires-Dist: networkx (>=3.2.1,<4.0.0)
Requires-Dist: numpy (>=2.0.0,<3.0.0)
Requires-Dist: openpyxl (>=3.1.2,<4.0.0)
Requires-Dist: p-tqdm (>=1.4.0,<2.0.0)
Requires-Dist: pandas (>=2.1.3,<3.0.0)
Requires-Dist: pip (>=24.1.2,<26.0.0)
Requires-Dist: scikit-fuzzy (>=0.4.2,<0.5.0)
Requires-Dist: scikit-learn (>=1.3.2,<2.0.0)
Requires-Dist: scipy (>=1.11.4,<2.0.0)
Requires-Dist: seaborn (>=0.13.0,<0.14.0)
Requires-Dist: semopy (>=2.3.10,<3.0.0)
Requires-Dist: setuptools (>=70,<79)
Requires-Dist: strenum (>=0.4.15,<0.5.0)
Project-URL: Documentation, https://gagnonanthony.github.io/NeuroStatX/
Project-URL: Repository, https://github.com/gagnonanthony/NeuroStatX.git
